lingtrain_aligner/__init__.py
lingtrain_aligner/aligner.py
lingtrain_aligner/api_request_parallel_processor.py
lingtrain_aligner/constants.py
lingtrain_aligner/corrector.py
lingtrain_aligner/helper.py
lingtrain_aligner/i18n.py
lingtrain_aligner/metrics.py
lingtrain_aligner/model_dispatcher.py
lingtrain_aligner/preprocessor.py
lingtrain_aligner/reader.py
lingtrain_aligner/resolver.py
lingtrain_aligner/saver.py
lingtrain_aligner/sentence_transformers_models.py
lingtrain_aligner/splitter.py
lingtrain_aligner/vis_helper.py
lingtrain_aligner-1.0.3.dist-info/licenses/LICENSE
lingtrain_aligner-1.0.3.dist-info/METADATA
lingtrain_aligner-1.0.3.dist-info/WHEEL
lingtrain_aligner-1.0.3.dist-info/top_level.txt
lingtrain_aligner-1.0.3.dist-info/RECORD
