Metadata-Version: 2.4
Name: lingtrain-aligner
Version: 1.0.3
Summary: Alignment tool for texts in different languages
Home-page: https://github.com/averkij/lingtrain-aligner
Author: Sergei Averkiev
Author-email: averoo@gmail.com
Project-URL: Bug Tracker, https://github.com/averkij/lingtrain-aligner/issues
Classifier: Programming Language :: Python :: 3
Classifier: License :: OSI Approved :: GNU General Public License v3 (GPLv3)
Classifier: Operating System :: OS Independent
Classifier: Topic :: Text Processing :: Linguistic
Requires-Python: >=3.6
License-File: LICENSE
Dynamic: license-file
